gomoku/__init__.py
gomoku/board.py
gomoku/game.py
gomoku/utils.py
gomoku/player/__init__.py
gomoku/player/human.py
gomoku/player/human_socket.py
gomoku/player/negamax.py
gomoku/player/simple.py
gomoku/player/threat_space.py
gomoku/threat/__init__.py
gomoku/threat/threat.py
gomoku/threat/threat_masks.py
gomoku/threat/threat_search.py
gomoku/threat/threat_space.py
gomoku-0.1.0.dist-info/METADATA
gomoku-0.1.0.dist-info/WHEEL
gomoku-0.1.0.dist-info/top_level.txt
gomoku-0.1.0.dist-info/RECORD
