Metadata-Version: 2.1
Name: gomoku
Version: 0.1.0
Summary: Gomoku AI
Home-page: UNKNOWN
Author: Allen Zhang
Author-email: UNKNOWN
License: UNKNOWN
Platform: UNKNOWN
Requires-Dist: pytest
Requires-Dist: gmpy2
